email_function_whl/__init__.py
email_function_whl/common_functions.py
email_function_whl/hash_functions.py
email_function_whl/mailer_function.py
email_function_whl-1.0.0.dist-info/METADATA
email_function_whl-1.0.0.dist-info/WHEEL
email_function_whl-1.0.0.dist-info/top_level.txt
email_function_whl-1.0.0.dist-info/RECORD
