Metadata-Version: 2.4
Name: email_function_whl
Version: 1.0.0
Summary: Simple email API client and utility functions for Fabric Notebook team
Author: Abhilash Ibrahimpatnam
Requires-Python: >=3.8
Requires-Dist: requests
